{
	"info": {
		"_postman_id": "08269159-678a-4138-8e60-de4cece2fc0f",
		"name": "Prueba Tecnica",
		"schema": "https://schema.getpostman.com/json/collection/v2.1.0/collection.json",
		"_exporter_id": "29865548"
	},
	"item": [
		{
			"name": "Agregar Usuario",
			"request": {
				"method": "POST",
				"header": [
					{
						"key": "Content-Type",
						"value": "application/json",
						"type": "text"
					}
				],
				"body": {
					"mode": "raw",
					"raw": "{\r\n    \"username\": \"yossu8989\",\r\n    \"password\": \"hola1234\"\r\n}",
					"options": {
						"raw": {
							"language": "json"
						}
					}
				},
				"url": {
					"raw": "http://localhost:3000/auth/register",
					"protocol": "http",
					"host": [
						"localhost"
					],
					"port": "3000",
					"path": [
						"auth",
						"register"
					]
				}
			},
			"response": []
		},
		{
			"name": "LOGIN",
			"request": {
				"method": "POST",
				"header": [
					{
						"key": "Content-Type",
						"value": "application/json",
						"type": "text"
					}
				],
				"body": {
					"mode": "raw",
					"raw": "{\r\n    \"username\": \"yossu8989\",\r\n    \"password\": \"hola1234\"\r\n}",
					"options": {
						"raw": {
							"language": "json"
						}
					}
				},
				"url": {
					"raw": "http://localhost:3000/auth/login",
					"protocol": "http",
					"host": [
						"localhost"
					],
					"port": "3000",
					"path": [
						"auth",
						"login"
					]
				}
			},
			"response": []
		}
	]
}